bambu_bootstrap
