Metadata-Version: 1.1
Name: bambu-bootstrap
Version: 2.2
Summary: Use Twitter's Bootstrap CSS framework to build your app. All the views Bambu uses all extend a base template which you create, that can be based on a skeleton Bootstrap template. Shortcut tags let you easily add breadcrumb trails and icons to your apps.
Home-page: http://pypi.python.org/pypi/bambu-bootstrap
Author: Steadman
Author-email: mark@steadman.io
License: UNKNOWN
Platform: UNKNOWN
Classifier: Development Status :: 4 - Beta
Classifier: Environment :: Web Environment
Classifier: Framework :: Django
